{
  "728520f-a": {
    "title": "Richmond: Bay Street - Canal Street", 
    "text": "Bay Street, at the N. E. corner of Canal Street, showing the Stapleton branch of the Corn Exchange Bank and Trust Company.\nApril, 1930\nP. L. Sperr\n", 
    "height": "400", 
    "width": "600", 
    "date": "1930", 
    "folder": "Bay Street & Canal Street, Staten Island, NY"
  }, 
  "728508f-a": {
    "title": "Richmond: Bay Street - Canal Street", 
    "text": "630 Bay Street, at the S.W. corner of Canal Street.\nMay 1, 1931\nP. L. Sperr\n", 
    "height": "600", 
    "width": "403", 
    "date": "1931", 
    "folder": "Bay Street & Canal Street, Staten Island, NY"
  }, 
  "728634f-a": {
    "title": "Richmond: Canal Street - Bay Street", 
    "text": "Canal Street, south side, east from (No. 56) but not including Bay Street, across the railroad crossing of the Staten Island Railros\nMay 25, 1935.\nP. L. Sperr.\n", 
    "height": "401", 
    "width": "600", 
    "date": "1935", 
    "folder": "Canal Street & Bay Street, Staten Island, NY"
  }, 
  "728519f-a": {
    "title": "Richmond: Bay Street - Canal Street", 
    "text": "Bay Street, north from Canal Street.\n9etober 4, 1936\nP. L. Sperr\n(s)\nThe same, some days later, showing improvewent operations.\nOctober 19, 1936\nP. L. Sperr\n", 
    "height": "405", 
    "width": "600", 
    "date": "1936", 
    "folder": "Bay Street & Canal Street, Staten Island, NY"
  }, 
  "728519f-b": {
    "title": "Richmond: Bay Street - Canal Street", 
    "text": "Bay Street, north from Canal Street.\n9etober 4, 1936\nP. L. Sperr\n(s)\nThe same, some days later, showing improvewent operations.\nOctober 19, 1936\nP. L. Sperr\n", 
    "height": "405", 
    "width": "600", 
    "date": "1936", 
    "folder": "Bay Street & Canal Street, Staten Island, NY"
  }
}