{
  "703200f-a": {
    "title": "", 
    "text": null, 
    "original_title": "Brooklyn: Avenue W - 73rd Street (East)", 
    "height": "470", 
    "width": "600", 
    "date": "1926", 
    "folder": "Avenue W & 73rd Street (East), Brooklyn, NY"
  }, 
  "703200f-b": {
    "title": "", 
    "text": null, 
    "original_title": "Brooklyn: Avenue W - 73rd Street (East)", 
    "height": "467", 
    "width": "600", 
    "date": "1926", 
    "folder": "Avenue W & 73rd Street (East), Brooklyn, NY"
  }, 
  "707154f-a": {
    "title": "", 
    "text": "(1)\nAVe. V, at the S.W. corner of East 73rd Street, showing the Steethoff-Bergen houee.\n1923.\nEugene L. Armbruster Collection.\n(2)\nThe same, a close up.\n1923.\nEugene L. Armbruster Collection.\n(3)\nThe same, a front view.\n1923.\nEugene L. Armbruster Collection.\n(4)\nThe same, showing the south side of the house.\nApril 1928.\nEugene L. Armbruster Collection.\n", 
    "original_title": "Brooklyn: Ave. B - 73rd St. E.", 
    "height": "467", 
    "width": "600", 
    "date": "", 
    "folder": "Ave. B & 73rd St. E., Brooklyn, NY"
  }, 
  "707154f-d": {
    "title": "", 
    "text": "(1)\nAVe. V, at the S.W. corner of East 73rd Street, showing the Steethoff-Bergen houee.\n1923.\nEugene L. Armbruster Collection.\n(2)\nThe same, a close up.\n1923.\nEugene L. Armbruster Collection.\n(3)\nThe same, a front view.\n1923.\nEugene L. Armbruster Collection.\n(4)\nThe same, showing the south side of the house.\nApril 1928.\nEugene L. Armbruster Collection.\n", 
    "original_title": "Brooklyn: Ave. B - 73rd St. E.", 
    "height": "443", 
    "width": "600", 
    "date": "", 
    "folder": "Ave. B & 73rd St. E., Brooklyn, NY"
  }, 
  "707154f-c": {
    "title": "", 
    "text": "(1)\nAVe. V, at the S.W. corner of East 73rd Street, showing the Steethoff-Bergen houee.\n1923.\nEugene L. Armbruster Collection.\n(2)\nThe same, a close up.\n1923.\nEugene L. Armbruster Collection.\n(3)\nThe same, a front view.\n1923.\nEugene L. Armbruster Collection.\n(4)\nThe same, showing the south side of the house.\nApril 1928.\nEugene L. Armbruster Collection.\n", 
    "original_title": "Brooklyn: Ave. B - 73rd St. E.", 
    "height": "472", 
    "width": "600", 
    "date": "", 
    "folder": "Ave. B & 73rd St. E., Brooklyn, NY"
  }, 
  "707154f-b": {
    "title": "", 
    "text": "(1)\nAVe. V, at the S.W. corner of East 73rd Street, showing the Steethoff-Bergen houee.\n1923.\nEugene L. Armbruster Collection.\n(2)\nThe same, a close up.\n1923.\nEugene L. Armbruster Collection.\n(3)\nThe same, a front view.\n1923.\nEugene L. Armbruster Collection.\n(4)\nThe same, showing the south side of the house.\nApril 1928.\nEugene L. Armbruster Collection.\n", 
    "original_title": "Brooklyn: Ave. B - 73rd St. E.", 
    "height": "468", 
    "width": "600", 
    "date": "", 
    "folder": "Ave. B & 73rd St. E., Brooklyn, NY"
  }
}