[
  {
    "date": "1938",
    "date_source": "nypl",
    "height": 406,
    "id": "704863f-a",
    "image_url": "https://oldnyc-assets.nypl.org/600px/704863f-a.jpg",
    "nypl_url": "https://digitalcollections.nypl.org/items/e3803f90-c535-012f-0266-58d385a7bc34",
    "original_title": "Brooklyn: Henry Street - Mill Street",
    "text": "740-722 Henry Street, west side, north from Mill to W. 9th Streets, showing at the corner in the foreground the Larsen Baking Co. plant. View No. 2 shows the Mill Street side of the bakery.\n\nJune 9, 1938\nViews 1 and 2\n\nP. L. Sperr\n",
    "thumb_url": "https://oldnyc-assets.nypl.org/thumb/704863f-a.jpg",
    "title": "",
    "width": 600,
    "years": [
      "1938"
    ]
  },
  {
    "date": "1938",
    "date_source": "nypl",
    "height": 405,
    "id": "704863f-b",
    "image_url": "https://oldnyc-assets.nypl.org/600px/704863f-b.jpg",
    "nypl_url": "https://digitalcollections.nypl.org/items/e3803f90-c535-012f-0266-58d385a7bc34",
    "original_title": "Brooklyn: Henry Street - Mill Street",
    "text": "740-722 Henry Street, west side, north from Mill to W. 9th Streets, showing at the corner in the foreground the Larsen Baking Co. plant. View No. 2 shows the Mill Street side of the bakery.\n\nJune 9, 1938\nViews 1 and 2\n\nP. L. Sperr\n",
    "thumb_url": "https://oldnyc-assets.nypl.org/thumb/704863f-b.jpg",
    "title": "",
    "width": 600,
    "years": [
      "1938"
    ]
  },
  {
    "date": "1938",
    "date_source": "nypl",
    "height": 404,
    "id": "705731f-a",
    "image_url": "https://oldnyc-assets.nypl.org/600px/705731f-a.jpg",
    "nypl_url": "https://digitalcollections.nypl.org/items/3f5af350-c537-012f-9a87-58d385a7bc34",
    "original_title": "Brooklyn: Mill Street - Henry Street",
    "text": "Mill Street, west from Henry Street, showing at the right the Larsen Baking Co. building.\n\nJune 9, 1938.\n\nP. L. Sperr\n",
    "thumb_url": "https://oldnyc-assets.nypl.org/thumb/705731f-a.jpg",
    "title": "",
    "width": 600,
    "years": [
      "1938"
    ]
  },
  {
    "date": "1938",
    "date_source": "nypl",
    "height": 404,
    "id": "705732f-a",
    "image_url": "https://oldnyc-assets.nypl.org/600px/705732f-a.jpg",
    "nypl_url": "https://digitalcollections.nypl.org/items/3fb18080-c537-012f-8678-58d385a7bc34",
    "original_title": "Brooklyn: Mill Street - Henry Street",
    "text": "Mill Street, east from Henry to Clinton Streets. This and surrounding areas are to be demolished. The Red Hook Housing Project has taken over the area to erect low rent multiple dwellings thereby slowly removing the slum areas of Greater New York.\n\nJune 9, 1938.\n\nP. L. Sperr\n",
    "thumb_url": "https://oldnyc-assets.nypl.org/thumb/705732f-a.jpg",
    "title": "",
    "width": 600,
    "years": [
      "1938"
    ]
  },
  {
    "date": "",
    "date_source": "nypl",
    "height": 383,
    "id": "704862f-a",
    "image_url": "https://oldnyc-assets.nypl.org/600px/704862f-a.jpg",
    "nypl_url": "https://digitalcollections.nypl.org/items/e3214b00-c535-012f-f17e-58d385a7bc34",
    "original_title": "Brooklyn: Henry Street - Mill Street",
    "text": null,
    "thumb_url": "https://oldnyc-assets.nypl.org/thumb/704862f-a.jpg",
    "title": "",
    "width": 600,
    "years": [
      ""
    ]
  }
]