[
  {
    "date": "1936",
    "date_source": "nypl",
    "height": 402,
    "id": "711117f-a",
    "image_url": "https://oldnyc-assets.nypl.org/600px/711117f-a.jpg",
    "nypl_url": "https://digitalcollections.nypl.org/items/d27172f0-c53f-012f-f213-58d385a7bc34",
    "original_title": "Manhattan: 12th Street (East) - Avenue D",
    "text": "East 12th Street, at Ave. D; as seen from the East River and East 11th Street.\nMarch 15, 1936.\n\nP. L. Sperr.\n",
    "thumb_url": "https://oldnyc-assets.nypl.org/thumb/711117f-a.jpg",
    "title": "",
    "width": 600,
    "years": [
      "1936"
    ]
  },
  {
    "date": "1936",
    "date_source": "nypl",
    "height": 400,
    "id": "719254f-a",
    "image_url": "https://oldnyc-assets.nypl.org/600px/719254f-a.jpg",
    "nypl_url": "https://digitalcollections.nypl.org/items/b0e45510-c54c-012f-f9bc-58d385a7bc34",
    "original_title": "Manhattan: Avenue D - 12th Street (East)",
    "text": "Ave. D, at the S.W. corner of East 12th Street. Also shown is East 12th Street, north side, west from, but not including Ave. D. Across clearance appears Dry dock Street, at, adjoining and south of the S.W. corner of East 12th Street.\n\nMarch 15, 1936.\n\nP. L. Sperr.\n",
    "thumb_url": "https://oldnyc-assets.nypl.org/thumb/719254f-a.jpg",
    "title": "",
    "width": 600,
    "years": [
      "1936"
    ]
  }
]