{
  "724644f-a": {
    "title": "Manhattan: West Street - Watts Street", 
    "text": "281-285, 286, 287 West Street, at and adioining the north corner\nof Watts Street, opposite Pier 31, North River.\n1v17.\n0ift of E. M. Jenks.\n", 
    "height": "451", 
    "width": "600", 
    "date": "1917", 
    "folder": "West Street & Watts Street, Manhattan, NY"
  }, 
  "724647f-a": {
    "title": "Manhattan: West Street - Watts Street", 
    "text": null, 
    "height": "427", 
    "width": "600", 
    "date": "1918", 
    "folder": "West Street & Watts Street, Manhattan, NY"
  }, 
  "724646f-a": {
    "title": "Manhattan: West Street - Watts Street", 
    "text": "West Street, east side, fromm Watts Street, opposite Pier 31, North River, to Canal Street, south fork (formerly Hoboken Street),\nopposite Pier 32.\nSeptember 27, 1927.\nP. L. Sperr.\n", 
    "height": "398", 
    "width": "600", 
    "date": "1927", 
    "folder": "West Street & Watts Street, Manhattan, NY"
  }, 
  "724645f-a": {
    "title": "Manhattan: West Street - Watts Street", 
    "text": "West Street, west side, north from Watts Street (Pier 3l, North\nRiver), showing Pier 34 being rebuilt.\nJuly 26, 1932.\nP. L. Sperr.\n", 
    "height": "398", 
    "width": "600", 
    "date": "1932", 
    "folder": "West Street & Watts Street, Manhattan, NY"
  }, 
  "724307f-a": {
    "title": "Manhattan: Watts Street - West Street", 
    "text": "153, 151-149 Watts Street, south side, between West and Washington\nStreets.\nJune 15, 1934.\nP. L. Sperr.\n", 
    "height": "600", 
    "width": "400", 
    "date": "", 
    "folder": "Watts Street & West Street, Manhattan, NY"
  }, 
  "724643f-b": {
    "title": "Manhattan: West Street - Watts Street", 
    "text": "(1)\nWest Street, east side, south from Watts Street, to and including\nDesbrosses Street.\nAugust 29, 1930.\nP. L. Sperr.\n(2)\nThe same, but showing a closer view of the S.E. corner of watts Street, also shown is Watts Street, south side, east from and including West Street, to and including Greenwich Streets.\nJune 15, 1934.\nP. L. Sperr.\n", 
    "height": "400", 
    "width": "600", 
    "date": "1930; 1934", 
    "folder": "West Street & Watts Street, Manhattan, NY"
  }, 
  "724643f-a": {
    "title": "Manhattan: West Street - Watts Street", 
    "text": "(1)\nWest Street, east side, south from Watts Street, to and including\nDesbrosses Street.\nAugust 29, 1930.\nP. L. Sperr.\n(2)\nThe same, but showing a closer view of the S.E. corner of watts Street, also shown is Watts Street, south side, east from and including West Street, to and including Greenwich Streets.\nJune 15, 1934.\nP. L. Sperr.\n", 
    "height": "399", 
    "width": "600", 
    "date": "1930; 1934", 
    "folder": "West Street & Watts Street, Manhattan, NY"
  }
}