{
  "725196f-a": {
    "width": 600, 
    "thumb_url": "http://oldnyc-assets.nypl.org/thumb/725196f-a.jpg", 
    "image_url": "http://oldnyc-assets.nypl.org/600px/725196f-a.jpg", 
    "title": "", 
    "date": "1931?", 
    "text": "Slat Avenue, north side, from 50th to Hobart Streets, showing\nPublic School No. 151.\nBoard of Education of the City of New York  about 1931\n", 
    "folder": "31st Avenue & 50th Street, Queens, NY", 
    "height": 478, 
    "original_title": "Queens: 31st Avenue - 50th Street", 
    "years": [
      "1931"
    ]
  }, 
  "725195f-a": {
    "width": 600, 
    "thumb_url": "http://oldnyc-assets.nypl.org/thumb/725195f-a.jpg", 
    "image_url": "http://oldnyc-assets.nypl.org/600px/725195f-a.jpg", 
    "title": "", 
    "date": "1932", 
    "text": "31st Avenue, north side, at 50th Street, showing Public School No. 151. The view is north from Broadway and on the right (telephone poles) is the Old Bowery Bay Road, now 51st\nStreet.\nP. L. Sperr  June 23, 1932\n", 
    "folder": "31st Avenue & 50th Street, Queens, NY", 
    "height": 403, 
    "original_title": "Queens: 31st Avenue - 50th Street", 
    "years": [
      "1932"
    ]
  }
}