[
  {
    "date": "1937",
    "date_source": "nypl",
    "folder": "3rd Avenue & 134th Street (East), Bronx, NY",
    "height": 401,
    "id": "700002f-a",
    "image_url": "https://oldnyc-assets.nypl.org/600px/700002f-a.jpg",
    "nypl_url": "https://digitalcollections.nypl.org/items/a5834cc0-c52e-012f-36a3-58d385a7bc34",
    "original_title": "Bronx: 3rd Avenue - 134th Street (East)",
    "text": "Third Ave. (foreground), at East 135th Street. The view is southeastward across the cleared area between East 135th and East 134th Streets which will be constructed into the westerly approach to the Triborough Bridge.\n\nP. L. Sperr. \nJuly 29, 1937.\n",
    "thumb_url": "https://oldnyc-assets.nypl.org/thumb/700002f-a.jpg",
    "title": "",
    "width": 600,
    "years": [
      "1937"
    ]
  }
]