{
  "702137f-a": {
    "width": 600, 
    "thumb_url": "http://oldnyc-assets.nypl.org/thumb/702137f-a.jpg", 
    "image_url": "http://oldnyc-assets.nypl.org/600px/702137f-a.jpg", 
    "title": "", 
    "date": "1928", 
    "text": "11 to 16 (left to right) Westchester Square (Lane Ave. ), west of,\nadjoining and at the N.W. corner of Benson Street.\nJuly 25, 1928.\nP. L. Sperr.\n", 
    "folder": "Lane Avenue & Benson Avenue, Bronx, NY", 
    "height": 396, 
    "original_title": "Bronx: Lane Avenue - Benson Avenue", 
    "years": [
      "1928"
    ]
  }
}