{
  "720349f-a": {
    "width": 369, 
    "thumb_url": "http://oldnyc-assets.nypl.org/thumb/720349f-a.jpg", 
    "image_url": "http://oldnyc-assets.nypl.org/600px/720349f-a.jpg", 
    "title": "", 
    "date": "1923", 
    "text": "Haven Avenue and about 176th Street, looking East from Riverside\nDrive.\nP. L. Sperr  Summmer 1923\n", 
    "folder": "Haven Avenue & 176th Street, Manhattan, NY", 
    "height": 600, 
    "original_title": "Manhattan: Haven Avenue - 176th Street", 
    "years": [
      "1923"
    ]
  }, 
  "720350f-a": {
    "width": 600, 
    "thumb_url": "http://oldnyc-assets.nypl.org/thumb/720350f-a.jpg", 
    "image_url": "http://oldnyc-assets.nypl.org/600px/720350f-a.jpg", 
    "title": "", 
    "date": "1924", 
    "text": "Haven Avenue, south from West 176th Street, showing several new apartments under construction. The far two, including the frame residence were removed subsequently and their sites are now a part of J. Hood Wright Park. At the right is W. 177th Street, continuing its winding way downhill to Riverside Drive.\nMay 18, 1924\nStandard Photographic Service\nGift of Borough President of Manhattan\n", 
    "folder": "Haven Avenue & 176th Street (West), Manhattan, NY", 
    "height": 483, 
    "original_title": "Manhattan: Haven Avenue - 176th Street (West)", 
    "years": [
      "1924"
    ]
  }
}